{
  "Q1817999": {
    "identifiers": [
      {
        "scheme": "wikidata",
        "identifier": "Q1817999"
      }
    ],
    "other_names": [
      {
        "lang": "pt",
        "name": "Eleições parlamentares na Ossétia do Sul em 2009",
        "note": "multilingual"
      },
      {
        "lang": "de",
        "name": "Parlamentswahlen in Südossetien 2009",
        "note": "multilingual"
      },
      {
        "lang": "pl",
        "name": "Wybory parlamentarne w Osetii Południowej w 2009 roku",
        "note": "multilingual"
      },
      {
        "lang": "ru",
        "name": "Парламентские выборы в Южной Осетии",
        "note": "multilingual"
      },
      {
        "lang": "en",
        "name": "South Ossetian parliamentary election, 2009",
        "note": "multilingual"
      },
      {
        "lang": "tr",
        "name": "2009 Güney Osetya parlamento seçimleri",
        "note": "multilingual"
      },
      {
        "lang": "uk",
        "name": "Парламентські вибори в Південній Осетії",
        "note": "multilingual"
      },
      {
        "lang": "pl",
        "name": "Wybory parlamentarne w Osetii Południowej",
        "note": "multilingual"
      },
      {
        "lang": "pl",
        "name": "Wybory parlamentarne w Osetii Południowej w 2009",
        "note": "multilingual"
      },
      {
        "lang": "ru",
        "name": "Выборы парламента Южной Осетии пятого созыва",
        "note": "multilingual"
      }
    ],
    "dates": [
      "2009"
    ]
  },
  "Q7568083": {
    "identifiers": [
      {
        "scheme": "wikidata",
        "identifier": "Q7568083"
      }
    ],
    "other_names": [
      {
        "lang": "en",
        "name": "South Ossetian parliamentary election, 2004",
        "note": "multilingual"
      }
    ],
    "dates": [
      "2004"
    ]
  },
  "Q16908867": {
    "identifiers": [
      {
        "scheme": "wikidata",
        "identifier": "Q16908867"
      }
    ],
    "other_names": [
      {
        "lang": "en",
        "name": "South Ossetian parliamentary election, 2014",
        "note": "multilingual"
      },
      {
        "lang": "ko",
        "name": "2014년 남오셰티아 총선",
        "note": "multilingual"
      },
      {
        "lang": "fr",
        "name": "Élections législatives sud-ossètes de 2014",
        "note": "multilingual"
      },
      {
        "lang": "ru",
        "name": "Парламентские выборы в Южной Осетии",
        "note": "multilingual"
      }
    ],
    "dates": [
      "2014-06-08"
    ]
  }
}