{
  "Q1708189": {
    "identifiers": [
      {
        "scheme": "wikidata",
        "identifier": "Q1708189"
      }
    ],
    "other_names": [
      {
        "lang": "ru",
        "name": "Парламентские выборы в Монако",
        "note": "multilingual"
      },
      {
        "lang": "fr",
        "name": "Élections nationales de Monaco de 2008",
        "note": "multilingual"
      },
      {
        "lang": "en",
        "name": "Monegasque parliamentary election, 2008",
        "note": "multilingual"
      },
      {
        "lang": "fr",
        "name": "Élections législatives de Monaco de 2008",
        "note": "multilingual"
      }
    ],
    "dates": [
      "2008"
    ]
  },
  "Q1763805": {
    "identifiers": [
      {
        "scheme": "wikidata",
        "identifier": "Q1763805"
      }
    ],
    "other_names": [
      {
        "lang": "ru",
        "name": "Парламентские выборы в Монако",
        "note": "multilingual"
      },
      {
        "lang": "en",
        "name": "Monegasque parliamentary election, 2013",
        "note": "multilingual"
      },
      {
        "lang": "fr",
        "name": "Élections nationales de Monaco de 2013",
        "note": "multilingual"
      },
      {
        "lang": "es",
        "name": "Elecciones parlamentarias de Mónaco de 2013",
        "note": "multilingual"
      },
      {
        "lang": "de",
        "name": "Parlamentswahl in Monaco 2013",
        "note": "multilingual"
      },
      {
        "lang": "de-ch",
        "name": "Parlamentswahl in Monaco 2013",
        "note": "multilingual"
      },
      {
        "lang": "en-ca",
        "name": "Monegasque parliamentary election, 2013",
        "note": "multilingual"
      },
      {
        "lang": "en-gb",
        "name": "Monegasque parliamentary election, 2013",
        "note": "multilingual"
      },
      {
        "lang": "uk",
        "name": "Парламентські вибори в Монако 2013",
        "note": "multilingual"
      },
      {
        "lang": "it",
        "name": "Elezioni legislative nel Principato di Monaco del 2013",
        "note": "multilingual"
      },
      {
        "lang": "nl",
        "name": "Monegasque parliamentary election",
        "note": "multilingual"
      },
      {
        "lang": "zh",
        "name": "2013年摩納哥大選",
        "note": "multilingual"
      },
      {
        "lang": "es",
        "name": "Elecciones parlamentarias en Mónaco de 2013",
        "note": "multilingual"
      }
    ],
    "dates": [
      "2013"
    ]
  },
  "Q6898875": {
    "identifiers": [
      {
        "scheme": "wikidata",
        "identifier": "Q6898875"
      }
    ],
    "other_names": [
      {
        "lang": "en",
        "name": "Monegasque parliamentary election, 1958",
        "note": "multilingual"
      }
    ],
    "dates": [
      "1958"
    ]
  },
  "Q6898879": {
    "identifiers": [
      {
        "scheme": "wikidata",
        "identifier": "Q6898879"
      }
    ],
    "other_names": [
      {
        "lang": "en",
        "name": "Monegasque parliamentary election, 1968",
        "note": "multilingual"
      }
    ],
    "dates": [
      "1968"
    ]
  },
  "Q6898881": {
    "identifiers": [
      {
        "scheme": "wikidata",
        "identifier": "Q6898881"
      }
    ],
    "other_names": [
      {
        "lang": "en",
        "name": "Monegasque parliamentary election, 1973",
        "note": "multilingual"
      }
    ],
    "dates": [
      "1973"
    ]
  },
  "Q6898882": {
    "identifiers": [
      {
        "scheme": "wikidata",
        "identifier": "Q6898882"
      }
    ],
    "other_names": [
      {
        "lang": "en",
        "name": "Monegasque parliamentary election, 1978",
        "note": "multilingual"
      }
    ],
    "dates": [
      "1978"
    ]
  },
  "Q6898884": {
    "identifiers": [
      {
        "scheme": "wikidata",
        "identifier": "Q6898884"
      }
    ],
    "other_names": [
      {
        "lang": "en",
        "name": "Monegasque parliamentary election, 1983",
        "note": "multilingual"
      }
    ],
    "dates": [
      "1983"
    ]
  },
  "Q6898885": {
    "identifiers": [
      {
        "scheme": "wikidata",
        "identifier": "Q6898885"
      }
    ],
    "other_names": [
      {
        "lang": "en",
        "name": "Monegasque parliamentary election, 1988",
        "note": "multilingual"
      }
    ],
    "dates": [
      "1988"
    ]
  },
  "Q6898887": {
    "identifiers": [
      {
        "scheme": "wikidata",
        "identifier": "Q6898887"
      }
    ],
    "other_names": [
      {
        "lang": "en",
        "name": "Monegasque parliamentary election, 1998",
        "note": "multilingual"
      }
    ],
    "dates": [
      "1998"
    ]
  },
  "Q6898891": {
    "identifiers": [
      {
        "scheme": "wikidata",
        "identifier": "Q6898891"
      }
    ],
    "other_names": [
      {
        "lang": "ro",
        "name": "Alegeri legislative în Monaco, 2003",
        "note": "multilingual"
      },
      {
        "lang": "en",
        "name": "Monegasque parliamentary election, 2003",
        "note": "multilingual"
      }
    ],
    "dates": [
      "2003"
    ]
  },
  "Q16934249": {
    "identifiers": [
      {
        "scheme": "wikidata",
        "identifier": "Q16934249"
      }
    ],
    "other_names": [
      {
        "lang": "en",
        "name": "Monegasque general election, 1963",
        "note": "multilingual"
      }
    ],
    "dates": [
      "1963"
    ]
  },
  "Q16934253": {
    "identifiers": [
      {
        "scheme": "wikidata",
        "identifier": "Q16934253"
      }
    ],
    "other_names": [
      {
        "lang": "en",
        "name": "Monegasque general election, 1993",
        "note": "multilingual"
      }
    ],
    "dates": [
      "1993"
    ]
  }
}